{"currentPage":1,"pageSize":500,"sort":null,"order":"asc","field":null,"treefield":null,"rows":[{"id":5198,"bid_month":201112,"system_time":"11:27:59","bid_people_num":26531,"lowest_price":50100,"lowest_price_time":"09:59:59","lowest_price_from":49800,"lowest_price_to":50400},{"id":5199,"bid_month":201112,"system_time":"11:28:00","bid_people_num":26531,"lowest_price":50100,"lowest_price_time":"09:59:59","lowest_price_from":49800,"lowest_price_to":50400},{"id":5200,"bid_month":201112,"system_time":"11:28:01","bid_people_num":26531,"lowest_price":50100,"lowest_price_time":"09:59:59","lowest_price_from":49800,"lowest_price_to":50400},{"id":5201,"bid_month":201112,"system_time":"11:28:02","bid_people_num":26531,"lowest_price":50100,"lowest_price_time":"09:59:59","lowest_price_from":49800,"lowest_price_to":50400},{"id":5202,"bid_month":201112,"system_time":"11:28:03","bid_people_num":26531,"lowest_price":50100,"lowest_price_time":"09:59:59","lowest_price_from":49800,"lowest_price_to":50400},{"id":5203,"bid_month":201112,"system_time":"11:28:04","bid_people_num":26531,"lowest_price":50100,"lowest_price_time":"09:59:59","lowest_price_from":49800,"lowest_price_to":50400},{"id":5204,"bid_month":201112,"system_time":"11:28:05","bid_people_num":26531,"lowest_price":50100,"lowest_price_time":"09:59:59","lowest_price_from":49800,"lowest_price_to":50400},{"id":5205,"bid_month":201112,"system_time":"11:28:06","bid_people_num":26531,"lowest_price":50100,"lowest_price_time":"09:59:59","lowest_price_from":49800,"lowest_price_to":50400},{"id":5206,"bid_month":201112,"system_time":"11:28:07","bid_people_num":26531,"lowest_price":50100,"lowest_price_time":"09:59:59","lowest_price_from":49800,"lowest_price_to":50400},{"id":5207,"bid_month":201112,"system_time":"11:28:08","bid_people_num":26531,"lowest_price":50100,"lowest_price_time":"09:59:59","lowest_price_from":49800,"lowest_price_to":50400},{"id":5208,"bid_month":201112,"system_time":"11:28:09","bid_people_num":26531,"lowest_price":50100,"lowest_price_time":"09:59:59","lowest_price_from":49800,"lowest_price_to":50400},{"id":5209,"bid_month":201112,"system_time":"11:28:10","bid_people_num":26531,"lowest_price":50100,"lowest_price_time":"09:59:59","lowest_price_from":49800,"lowest_price_to":50400},{"id":5210,"bid_month":201112,"system_time":"11:28:11","bid_people_num":26531,"lowest_price":50200,"lowest_price_time":"09:59:59","lowest_price_from":49900,"lowest_price_to":50500},{"id":5211,"bid_month":201112,"system_time":"11:28:12","bid_people_num":26531,"lowest_price":50200,"lowest_price_time":"09:59:59","lowest_price_from":49900,"lowest_price_to":50500},{"id":5212,"bid_month":201112,"system_time":"11:28:13","bid_people_num":26531,"lowest_price":50200,"lowest_price_time":"09:59:59","lowest_price_from":49900,"lowest_price_to":50500},{"id":5213,"bid_month":201112,"system_time":"11:28:14","bid_people_num":26531,"lowest_price":50200,"lowest_price_time":"09:59:59","lowest_price_from":49900,"lowest_price_to":50500},{"id":5214,"bid_month":201112,"system_time":"11:28:15","bid_people_num":26531,"lowest_price":50200,"lowest_price_time":"09:59:59","lowest_price_from":49900,"lowest_price_to":50500},{"id":5215,"bid_month":201112,"system_time":"11:28:16","bid_people_num":26531,"lowest_price":50200,"lowest_price_time":"09:59:59","lowest_price_from":49900,"lowest_price_to":50500},{"id":5216,"bid_month":201112,"system_time":"11:28:17","bid_people_num":26531,"lowest_price":50200,"lowest_price_time":"09:59:59","lowest_price_from":49900,"lowest_price_to":50500},{"id":5217,"bid_month":201112,"system_time":"11:28:18","bid_people_num":26531,"lowest_price":50200,"lowest_price_time":"09:59:59","lowest_price_from":49900,"lowest_price_to":50500},{"id":5218,"bid_month":201112,"system_time":"11:28:19","bid_people_num":26531,"lowest_price":50200,"lowest_price_time":"09:59:59","lowest_price_from":49900,"lowest_price_to":50500},{"id":5219,"bid_month":201112,"system_time":"11:28:20","bid_people_num":26531,"lowest_price":50200,"lowest_price_time":"09:59:59","lowest_price_from":49900,"lowest_price_to":50500},{"id":5220,"bid_month":201112,"system_time":"11:28:21","bid_people_num":26531,"lowest_price":50200,"lowest_price_time":"09:59:59","lowest_price_from":49900,"lowest_price_to":50500},{"id":5221,"bid_month":201112,"system_time":"11:28:22","bid_people_num":26531,"lowest_price":50200,"lowest_price_time":"09:59:59","lowest_price_from":49900,"lowest_price_to":50500},{"id":5222,"bid_month":201112,"system_time":"11:28:23","bid_people_num":26531,"lowest_price":50200,"lowest_price_time":"09:59:59","lowest_price_from":49900,"lowest_price_to":50500},{"id":5223,"bid_month":201112,"system_time":"11:28:24","bid_people_num":26531,"lowest_price":50200,"lowest_price_time":"09:59:59","lowest_price_from":49900,"lowest_price_to":50500},{"id":5224,"bid_month":201112,"system_time":"11:28:25","bid_people_num":26531,"lowest_price":50200,"lowest_price_time":"09:59:59","lowest_price_from":49900,"lowest_price_to":50500},{"id":5225,"bid_month":201112,"system_time":"11:28:26","bid_people_num":26531,"lowest_price":50200,"lowest_price_time":"09:59:59","lowest_price_from":49900,"lowest_price_to":50500},{"id":5226,"bid_month":201112,"system_time":"11:28:27","bid_people_num":26531,"lowest_price":50200,"lowest_price_time":"09:59:59","lowest_price_from":49900,"lowest_price_to":50500},{"id":5227,"bid_month":201112,"system_time":"11:28:28","bid_people_num":26531,"lowest_price":50200,"lowest_price_time":"09:59:59","lowest_price_from":49900,"lowest_price_to":50500},{"id":5228,"bid_month":201112,"system_time":"11:28:29","bid_people_num":26531,"lowest_price":50300,"lowest_price_time":"09:59:59","lowest_price_from":50000,"lowest_price_to":50600},{"id":5229,"bid_month":201112,"system_time":"11:28:30","bid_people_num":26531,"lowest_price":50300,"lowest_price_time":"09:59:59","lowest_price_from":50000,"lowest_price_to":50600},{"id":5230,"bid_month":201112,"system_time":"11:28:31","bid_people_num":26531,"lowest_price":50300,"lowest_price_time":"09:59:59","lowest_price_from":50000,"lowest_price_to":50600},{"id":5231,"bid_month":201112,"system_time":"11:28:32","bid_people_num":26531,"lowest_price":50300,"lowest_price_time":"09:59:59","lowest_price_from":50000,"lowest_price_to":50600},{"id":5232,"bid_month":201112,"system_time":"11:28:33","bid_people_num":26531,"lowest_price":50300,"lowest_price_time":"09:59:59","lowest_price_from":50000,"lowest_price_to":50600},{"id":5233,"bid_month":201112,"system_time":"11:28:34","bid_people_num":26531,"lowest_price":50300,"lowest_price_time":"09:59:59","lowest_price_from":50000,"lowest_price_to":50600},{"id":5234,"bid_month":201112,"system_time":"11:28:35","bid_people_num":26531,"lowest_price":50300,"lowest_price_time":"09:59:59","lowest_price_from":50000,"lowest_price_to":50600},{"id":5235,"bid_month":201112,"system_time":"11:28:36","bid_people_num":26531,"lowest_price":50300,"lowest_price_time":"09:59:59","lowest_price_from":50000,"lowest_price_to":50600},{"id":5236,"bid_month":201112,"system_time":"11:28:37","bid_people_num":26531,"lowest_price":50300,"lowest_price_time":"09:59:59","lowest_price_from":50000,"lowest_price_to":50600},{"id":5237,"bid_month":201112,"system_time":"11:28:38","bid_people_num":26531,"lowest_price":50300,"lowest_price_time":"09:59:59","lowest_price_from":50000,"lowest_price_to":50600},{"id":5238,"bid_month":201112,"system_time":"11:28:39","bid_people_num":26531,"lowest_price":50300,"lowest_price_time":"09:59:59","lowest_price_from":50000,"lowest_price_to":50600},{"id":5239,"bid_month":201112,"system_time":"11:28:40","bid_people_num":26531,"lowest_price":50300,"lowest_price_time":"09:59:59","lowest_price_from":50000,"lowest_price_to":50600},{"id":5240,"bid_month":201112,"system_time":"11:28:41","bid_people_num":26531,"lowest_price":50300,"lowest_price_time":"09:59:59","lowest_price_from":50000,"lowest_price_to":50600},{"id":5241,"bid_month":201112,"system_time":"11:28:42","bid_people_num":26531,"lowest_price":50300,"lowest_price_time":"09:59:59","lowest_price_from":50000,"lowest_price_to":50600},{"id":5242,"bid_month":201112,"system_time":"11:28:43","bid_people_num":26531,"lowest_price":50300,"lowest_price_time":"09:59:59","lowest_price_from":50000,"lowest_price_to":50600},{"id":5243,"bid_month":201112,"system_time":"11:28:44","bid_people_num":26531,"lowest_price":50300,"lowest_price_time":"09:59:59","lowest_price_from":50000,"lowest_price_to":50600},{"id":5244,"bid_month":201112,"system_time":"11:28:45","bid_people_num":26531,"lowest_price":50300,"lowest_price_time":"09:59:59","lowest_price_from":50000,"lowest_price_to":50600},{"id":5245,"bid_month":201112,"system_time":"11:28:46","bid_people_num":26531,"lowest_price":50300,"lowest_price_time":"09:59:59","lowest_price_from":50000,"lowest_price_to":50600},{"id":5246,"bid_month":201112,"system_time":"11:28:47","bid_people_num":26531,"lowest_price":50300,"lowest_price_time":"09:59:59","lowest_price_from":50000,"lowest_price_to":50600},{"id":5247,"bid_month":201112,"system_time":"11:28:48","bid_people_num":26531,"lowest_price":50300,"lowest_price_time":"09:59:59","lowest_price_from":50000,"lowest_price_to":50600},{"id":5248,"bid_month":201112,"system_time":"11:28:49","bid_people_num":26531,"lowest_price":50300,"lowest_price_time":"09:59:59","lowest_price_from":50000,"lowest_price_to":50600},{"id":5249,"bid_month":201112,"system_time":"11:28:50","bid_people_num":26531,"lowest_price":50300,"lowest_price_time":"09:59:59","lowest_price_from":50000,"lowest_price_to":50600},{"id":5250,"bid_month":201112,"system_time":"11:28:51","bid_people_num":26531,"lowest_price":50300,"lowest_price_time":"09:59:59","lowest_price_from":50000,"lowest_price_to":50600},{"id":5251,"bid_month":201112,"system_time":"11:28:52","bid_people_num":26531,"lowest_price":50300,"lowest_price_time":"09:59:59","lowest_price_from":50000,"lowest_price_to":50600},{"id":5252,"bid_month":201112,"system_time":"11:28:53","bid_people_num":26531,"lowest_price":50300,"lowest_price_time":"09:59:59","lowest_price_from":50000,"lowest_price_to":50600},{"id":5253,"bid_month":201112,"system_time":"11:28:54","bid_people_num":26531,"lowest_price":50300,"lowest_price_time":"09:59:59","lowest_price_from":50000,"lowest_price_to":50600},{"id":5254,"bid_month":201112,"system_time":"11:28:55","bid_people_num":26531,"lowest_price":50300,"lowest_price_time":"09:59:59","lowest_price_from":50000,"lowest_price_to":50600},{"id":5255,"bid_month":201112,"system_time":"11:28:56","bid_people_num":26531,"lowest_price":50300,"lowest_price_time":"09:59:59","lowest_price_from":50000,"lowest_price_to":50600},{"id":5256,"bid_month":201112,"system_time":"11:28:57","bid_people_num":26531,"lowest_price":50300,"lowest_price_time":"09:59:59","lowest_price_from":50000,"lowest_price_to":50600},{"id":5257,"bid_month":201112,"system_time":"11:28:58","bid_people_num":26531,"lowest_price":50300,"lowest_price_time":"09:59:59","lowest_price_from":50000,"lowest_price_to":50600},{"id":5258,"bid_month":201112,"system_time":"11:28:59","bid_people_num":26531,"lowest_price":50300,"lowest_price_time":"09:59:59","lowest_price_from":50000,"lowest_price_to":50600},{"id":5259,"bid_month":201112,"system_time":"11:29:00","bid_people_num":26531,"lowest_price":50300,"lowest_price_time":"09:59:59","lowest_price_from":50000,"lowest_price_to":50600},{"id":5260,"bid_month":201112,"system_time":"11:29:01","bid_people_num":26531,"lowest_price":50300,"lowest_price_time":"09:59:59","lowest_price_from":50000,"lowest_price_to":50600},{"id":5261,"bid_month":201112,"system_time":"11:29:02","bid_people_num":26531,"lowest_price":50300,"lowest_price_time":"09:59:59","lowest_price_from":50000,"lowest_price_to":50600},{"id":5262,"bid_month":201112,"system_time":"11:29:03","bid_people_num":26531,"lowest_price":50300,"lowest_price_time":"09:59:59","lowest_price_from":50000,"lowest_price_to":50600},{"id":5263,"bid_month":201112,"system_time":"11:29:04","bid_people_num":26531,"lowest_price":50300,"lowest_price_time":"09:59:59","lowest_price_from":50000,"lowest_price_to":50600},{"id":5264,"bid_month":201112,"system_time":"11:29:05","bid_people_num":26531,"lowest_price":50300,"lowest_price_time":"09:59:59","lowest_price_from":50000,"lowest_price_to":50600},{"id":5265,"bid_month":201112,"system_time":"11:29:06","bid_people_num":26531,"lowest_price":50300,"lowest_price_time":"09:59:59","lowest_price_from":50000,"lowest_price_to":50600},{"id":5266,"bid_month":201112,"system_time":"11:29:07","bid_people_num":26531,"lowest_price":50300,"lowest_price_time":"09:59:59","lowest_price_from":50000,"lowest_price_to":50600},{"id":5267,"bid_month":201112,"system_time":"11:29:08","bid_people_num":26531,"lowest_price":50300,"lowest_price_time":"09:59:59","lowest_price_from":50000,"lowest_price_to":50600},{"id":5268,"bid_month":201112,"system_time":"11:29:09","bid_people_num":26531,"lowest_price":50300,"lowest_price_time":"09:59:59","lowest_price_from":50000,"lowest_price_to":50600},{"id":5269,"bid_month":201112,"system_time":"11:29:10","bid_people_num":26531,"lowest_price":50300,"lowest_price_time":"09:59:59","lowest_price_from":50000,"lowest_price_to":50600},{"id":5270,"bid_month":201112,"system_time":"11:29:11","bid_people_num":26531,"lowest_price":50300,"lowest_price_time":"09:59:59","lowest_price_from":50000,"lowest_price_to":50600},{"id":5271,"bid_month":201112,"system_time":"11:29:12","bid_people_num":26531,"lowest_price":50300,"lowest_price_time":"09:59:59","lowest_price_from":50000,"lowest_price_to":50600},{"id":5272,"bid_month":201112,"system_time":"11:29:13","bid_people_num":26531,"lowest_price":50300,"lowest_price_time":"09:59:59","lowest_price_from":50000,"lowest_price_to":50600},{"id":5273,"bid_month":201112,"system_time":"11:29:14","bid_people_num":26531,"lowest_price":50300,"lowest_price_time":"09:59:59","lowest_price_from":50000,"lowest_price_to":50600},{"id":5274,"bid_month":201112,"system_time":"11:29:15","bid_people_num":26531,"lowest_price":50300,"lowest_price_time":"09:59:59","lowest_price_from":50000,"lowest_price_to":50600},{"id":5275,"bid_month":201112,"system_time":"11:29:16","bid_people_num":26531,"lowest_price":50300,"lowest_price_time":"09:59:59","lowest_price_from":50000,"lowest_price_to":50600},{"id":5276,"bid_month":201112,"system_time":"11:29:17","bid_people_num":26531,"lowest_price":50300,"lowest_price_time":"09:59:59","lowest_price_from":50000,"lowest_price_to":50600},{"id":5277,"bid_month":201112,"system_time":"11:29:18","bid_people_num":26531,"lowest_price":50300,"lowest_price_time":"09:59:59","lowest_price_from":50000,"lowest_price_to":50600},{"id":5278,"bid_month":201112,"system_time":"11:29:19","bid_people_num":26531,"lowest_price":50300,"lowest_price_time":"09:59:59","lowest_price_from":50000,"lowest_price_to":50600},{"id":5279,"bid_month":201112,"system_time":"11:29:20","bid_people_num":26531,"lowest_price":50300,"lowest_price_time":"09:59:59","lowest_price_from":50000,"lowest_price_to":50600},{"id":5280,"bid_month":201112,"system_time":"11:29:21","bid_people_num":26531,"lowest_price":50300,"lowest_price_time":"09:59:59","lowest_price_from":50000,"lowest_price_to":50600},{"id":5281,"bid_month":201112,"system_time":"11:29:22","bid_people_num":26531,"lowest_price":50300,"lowest_price_time":"09:59:59","lowest_price_from":50000,"lowest_price_to":50600},{"id":5282,"bid_month":201112,"system_time":"11:29:23","bid_people_num":26531,"lowest_price":50300,"lowest_price_time":"09:59:59","lowest_price_from":50000,"lowest_price_to":50600},{"id":5283,"bid_month":201112,"system_time":"11:29:24","bid_people_num":26531,"lowest_price":50400,"lowest_price_time":"09:59:59","lowest_price_from":50100,"lowest_price_to":50700},{"id":5284,"bid_month":201112,"system_time":"11:29:25","bid_people_num":26531,"lowest_price":50400,"lowest_price_time":"09:59:59","lowest_price_from":50100,"lowest_price_to":50700},{"id":5285,"bid_month":201112,"system_time":"11:29:26","bid_people_num":26531,"lowest_price":50400,"lowest_price_time":"09:59:59","lowest_price_from":50100,"lowest_price_to":50700},{"id":5286,"bid_month":201112,"system_time":"11:29:27","bid_people_num":26531,"lowest_price":50400,"lowest_price_time":"09:59:59","lowest_price_from":50100,"lowest_price_to":50700},{"id":5287,"bid_month":201112,"system_time":"11:29:28","bid_people_num":26531,"lowest_price":50400,"lowest_price_time":"09:59:59","lowest_price_from":50100,"lowest_price_to":50700},{"id":5288,"bid_month":201112,"system_time":"11:29:29","bid_people_num":26531,"lowest_price":50400,"lowest_price_time":"09:59:59","lowest_price_from":50100,"lowest_price_to":50700},{"id":5289,"bid_month":201112,"system_time":"11:29:30","bid_people_num":26531,"lowest_price":50500,"lowest_price_time":"09:59:59","lowest_price_from":50200,"lowest_price_to":50800},{"id":5290,"bid_month":201112,"system_time":"11:29:31","bid_people_num":26531,"lowest_price":50500,"lowest_price_time":"09:59:59","lowest_price_from":50200,"lowest_price_to":50800},{"id":5291,"bid_month":201112,"system_time":"11:29:32","bid_people_num":26531,"lowest_price":50500,"lowest_price_time":"09:59:59","lowest_price_from":50200,"lowest_price_to":50800},{"id":5292,"bid_month":201112,"system_time":"11:29:33","bid_people_num":26531,"lowest_price":50500,"lowest_price_time":"09:59:59","lowest_price_from":50200,"lowest_price_to":50800},{"id":5293,"bid_month":201112,"system_time":"11:29:34","bid_people_num":26531,"lowest_price":50500,"lowest_price_time":"09:59:59","lowest_price_from":50200,"lowest_price_to":50800},{"id":5294,"bid_month":201112,"system_time":"11:29:35","bid_people_num":26531,"lowest_price":50600,"lowest_price_time":"09:59:59","lowest_price_from":50300,"lowest_price_to":50900},{"id":5295,"bid_month":201112,"system_time":"11:29:36","bid_people_num":26531,"lowest_price":50600,"lowest_price_time":"09:59:59","lowest_price_from":50300,"lowest_price_to":50900},{"id":5296,"bid_month":201112,"system_time":"11:29:37","bid_people_num":26531,"lowest_price":50600,"lowest_price_time":"09:59:59","lowest_price_from":50300,"lowest_price_to":50900},{"id":5297,"bid_month":201112,"system_time":"11:29:38","bid_people_num":26531,"lowest_price":50600,"lowest_price_time":"09:59:59","lowest_price_from":50300,"lowest_price_to":50900},{"id":5298,"bid_month":201112,"system_time":"11:29:39","bid_people_num":26531,"lowest_price":50600,"lowest_price_time":"09:59:59","lowest_price_from":50300,"lowest_price_to":50900},{"id":5299,"bid_month":201112,"system_time":"11:29:40","bid_people_num":26531,"lowest_price":50600,"lowest_price_time":"09:59:59","lowest_price_from":50300,"lowest_price_to":50900},{"id":5300,"bid_month":201112,"system_time":"11:29:41","bid_people_num":26531,"lowest_price":50600,"lowest_price_time":"09:59:59","lowest_price_from":50300,"lowest_price_to":50900},{"id":5301,"bid_month":201112,"system_time":"11:29:42","bid_people_num":26531,"lowest_price":50600,"lowest_price_time":"09:59:59","lowest_price_from":50300,"lowest_price_to":50900},{"id":5302,"bid_month":201112,"system_time":"11:29:43","bid_people_num":26531,"lowest_price":50600,"lowest_price_time":"09:59:59","lowest_price_from":50300,"lowest_price_to":50900},{"id":5303,"bid_month":201112,"system_time":"11:29:44","bid_people_num":26531,"lowest_price":50600,"lowest_price_time":"09:59:59","lowest_price_from":50300,"lowest_price_to":50900},{"id":5304,"bid_month":201112,"system_time":"11:29:45","bid_people_num":26531,"lowest_price":50600,"lowest_price_time":"09:59:59","lowest_price_from":50300,"lowest_price_to":50900},{"id":5305,"bid_month":201112,"system_time":"11:29:46","bid_people_num":26531,"lowest_price":50700,"lowest_price_time":"09:59:59","lowest_price_from":50400,"lowest_price_to":51000},{"id":5306,"bid_month":201112,"system_time":"11:29:47","bid_people_num":26531,"lowest_price":50700,"lowest_price_time":"09:59:59","lowest_price_from":50400,"lowest_price_to":51000},{"id":5307,"bid_month":201112,"system_time":"11:29:48","bid_people_num":26531,"lowest_price":50700,"lowest_price_time":"09:59:59","lowest_price_from":50400,"lowest_price_to":51000},{"id":5308,"bid_month":201112,"system_time":"11:29:49","bid_people_num":26531,"lowest_price":50800,"lowest_price_time":"09:59:59","lowest_price_from":50500,"lowest_price_to":51100},{"id":5309,"bid_month":201112,"system_time":"11:29:50","bid_people_num":26531,"lowest_price":50800,"lowest_price_time":"09:59:59","lowest_price_from":50500,"lowest_price_to":51100},{"id":5310,"bid_month":201112,"system_time":"11:29:51","bid_people_num":26531,"lowest_price":50800,"lowest_price_time":"09:59:59","lowest_price_from":50500,"lowest_price_to":51100},{"id":5311,"bid_month":201112,"system_time":"11:29:52","bid_people_num":26531,"lowest_price":50800,"lowest_price_time":"09:59:59","lowest_price_from":50500,"lowest_price_to":51100},{"id":5312,"bid_month":201112,"system_time":"11:29:53","bid_people_num":26531,"lowest_price":50800,"lowest_price_time":"09:59:59","lowest_price_from":50500,"lowest_price_to":51100},{"id":5313,"bid_month":201112,"system_time":"11:29:54","bid_people_num":26531,"lowest_price":50900,"lowest_price_time":"09:59:59","lowest_price_from":50600,"lowest_price_to":51200},{"id":5314,"bid_month":201112,"system_time":"11:29:55","bid_people_num":26531,"lowest_price":50900,"lowest_price_time":"09:59:59","lowest_price_from":50600,"lowest_price_to":51200},{"id":5315,"bid_month":201112,"system_time":"11:29:56","bid_people_num":26531,"lowest_price":50900,"lowest_price_time":"09:59:59","lowest_price_from":50600,"lowest_price_to":51200},{"id":5316,"bid_month":201112,"system_time":"11:29:57","bid_people_num":26531,"lowest_price":51000,"lowest_price_time":"09:59:59","lowest_price_from":50700,"lowest_price_to":51300},{"id":5317,"bid_month":201112,"system_time":"11:29:58","bid_people_num":26531,"lowest_price":51000,"lowest_price_time":"09:59:59","lowest_price_from":50700,"lowest_price_to":51300},{"id":5318,"bid_month":201112,"system_time":"11:29:59","bid_people_num":26531,"lowest_price":51000,"lowest_price_time":"09:59:59","lowest_price_from":50700,"lowest_price_to":51300}],"total":121,"footer":null}